flask_jwt_persistency/__init__.py
flask_jwt_persistency-0.0.3.dist-info/LICENSE
flask_jwt_persistency-0.0.3.dist-info/METADATA
flask_jwt_persistency-0.0.3.dist-info/WHEEL
flask_jwt_persistency-0.0.3.dist-info/top_level.txt
flask_jwt_persistency-0.0.3.dist-info/RECORD
